random_password_toolkit/__init__.py
random_password_toolkit/encryptor.py
random_password_toolkit/generator.py
random_password_toolkit/random_number_generator.py
random_password_toolkit/strength_checker.py
random_password_toolkit-1.0.2.dist-info/licenses/LICENSE
random_password_toolkit-1.0.2.dist-info/METADATA
random_password_toolkit-1.0.2.dist-info/WHEEL
random_password_toolkit-1.0.2.dist-info/top_level.txt
random_password_toolkit-1.0.2.dist-info/RECORD
