Metadata-Version: 2.4
Name: random-password-toolkit
Version: 1.0.2
Summary: random-password-toolkit is a robust Python package for generating and managing random passwords with advanced features, including encryption, decryption, strength checking, and customizable generation options. This package is ideal for Python developers looking for a secure and feature-rich solution for handling password-related tasks.
Home-page: https://github.com/krishnatadi/random-password-toolkit-python
Author: krishna Tadi
License: MIT
Project-URL: Documentation, https://github.com/krishnatadi/random-password-toolkit-python#readme
Project-URL: Source, https://github.com/krishnatadi/random-password-toolkit-python
Project-URL: Issue Tracker, https://github.com/krishnatadi/random-password-toolkit-python/issues
Keywords: ""random password generator","password strength checker","password encryption","password decryption","secure password management","customizable password generation","Python password toolkit","Random number generation"
Classifier: Programming Language :: Python :: 3
Classifier: License :: OSI Approved :: MIT License
Classifier: Operating System :: OS Independent
Requires-Python: >=3.6
License-File: LICENSE
Requires-Dist: cryptography>=38.0.0
Dynamic: author
Dynamic: classifier
Dynamic: description
Dynamic: description-content-type
Dynamic: home-page
Dynamic: keywords
Dynamic: license
Dynamic: license-file
Dynamic: project-url
Dynamic: requires-dist
Dynamic: requires-python
Dynamic: summary
